{
  "updated": "20260629T143951Z",
  "data": {
    "HOU": {
      "battingRate": 0.596,
      "battingWon": 59,
      "battingAttempted": 99,
      "netOverturns": 23.4,
      "totalVsExpected": 19.4,
      "grade": "A-"
    },
    "KC": {
      "battingRate": 0.526,
      "battingWon": 41,
      "battingAttempted": 78,
      "netOverturns": 12.9,
      "totalVsExpected": 26.8,
      "grade": "B+"
    },
    "NYM": {
      "battingRate": 0.51,
      "battingWon": 51,
      "battingAttempted": 100,
      "netOverturns": 11.6,
      "totalVsExpected": 16.6,
      "grade": "B"
    },
    "CIN": {
      "battingRate": 0.562,
      "battingWon": 54,
      "battingAttempted": 96,
      "netOverturns": 11.5,
      "totalVsExpected": 11.2,
      "grade": "A-"
    },
    "AZ": {
      "battingRate": 0.559,
      "battingWon": 38,
      "battingAttempted": 68,
      "netOverturns": 10.8,
      "totalVsExpected": 9.7,
      "grade": "B+"
    },
    "LAD": {
      "battingRate": 0.524,
      "battingWon": 43,
      "battingAttempted": 82,
      "netOverturns": 8.4,
      "totalVsExpected": 0.7,
      "grade": "B+"
    },
    "ATH": {
      "battingRate": 0.551,
      "battingWon": 43,
      "battingAttempted": 78,
      "netOverturns": 8.2,
      "totalVsExpected": 1.6,
      "grade": "B+"
    },
    "DET": {
      "battingRate": 0.523,
      "battingWon": 45,
      "battingAttempted": 86,
      "netOverturns": 7.8,
      "totalVsExpected": 21.1,
      "grade": "B+"
    },
    "PHI": {
      "battingRate": 0.471,
      "battingWon": 41,
      "battingAttempted": 87,
      "netOverturns": 5.3,
      "totalVsExpected": 22.3,
      "grade": "C+"
    },
    "NYY": {
      "battingRate": 0.495,
      "battingWon": 45,
      "battingAttempted": 91,
      "netOverturns": 5.1,
      "totalVsExpected": 8.0,
      "grade": "B"
    },
    "STL": {
      "battingRate": 0.478,
      "battingWon": 32,
      "battingAttempted": 67,
      "netOverturns": 4.2,
      "totalVsExpected": -4.6,
      "grade": "C+"
    },
    "MIL": {
      "battingRate": 0.407,
      "battingWon": 22,
      "battingAttempted": 54,
      "netOverturns": 2.5,
      "totalVsExpected": 4.3,
      "grade": "C"
    },
    "TEX": {
      "battingRate": 0.473,
      "battingWon": 35,
      "battingAttempted": 74,
      "netOverturns": 2.4,
      "totalVsExpected": -7.3,
      "grade": "C+"
    },
    "CHC": {
      "battingRate": 0.423,
      "battingWon": 33,
      "battingAttempted": 78,
      "netOverturns": 1.8,
      "totalVsExpected": 7.1,
      "grade": "C"
    },
    "CWS": {
      "battingRate": 0.479,
      "battingWon": 35,
      "battingAttempted": 73,
      "netOverturns": 1.5,
      "totalVsExpected": -8.6,
      "grade": "C+"
    },
    "SD": {
      "battingRate": 0.436,
      "battingWon": 24,
      "battingAttempted": 55,
      "netOverturns": 0.2,
      "totalVsExpected": 1.8,
      "grade": "C"
    },
    "BAL": {
      "battingRate": 0.5,
      "battingWon": 46,
      "battingAttempted": 92,
      "netOverturns": -0.7,
      "totalVsExpected": -7.5,
      "grade": "B"
    },
    "MIN": {
      "battingRate": 0.482,
      "battingWon": 53,
      "battingAttempted": 110,
      "netOverturns": -1.0,
      "totalVsExpected": 2.7,
      "grade": "B"
    },
    "SF": {
      "battingRate": 0.5,
      "battingWon": 40,
      "battingAttempted": 80,
      "netOverturns": -1.7,
      "totalVsExpected": -13.5,
      "grade": "B"
    },
    "MIA": {
      "battingRate": 0.5,
      "battingWon": 31,
      "battingAttempted": 62,
      "netOverturns": -3.5,
      "totalVsExpected": 12.0,
      "grade": "B"
    },
    "BOS": {
      "battingRate": 0.453,
      "battingWon": 34,
      "battingAttempted": 75,
      "netOverturns": -3.6,
      "totalVsExpected": -8.5,
      "grade": "C+"
    },
    "TOR": {
      "battingRate": 0.475,
      "battingWon": 38,
      "battingAttempted": 80,
      "netOverturns": -4.5,
      "totalVsExpected": -1.3,
      "grade": "C+"
    },
    "TB": {
      "battingRate": 0.453,
      "battingWon": 34,
      "battingAttempted": 75,
      "netOverturns": -4.5,
      "totalVsExpected": -16.0,
      "grade": "C+"
    },
    "SEA": {
      "battingRate": 0.439,
      "battingWon": 36,
      "battingAttempted": 82,
      "netOverturns": -6.4,
      "totalVsExpected": -10.4,
      "grade": "C"
    },
    "WSH": {
      "battingRate": 0.42,
      "battingWon": 29,
      "battingAttempted": 69,
      "netOverturns": -6.4,
      "totalVsExpected": -10.2,
      "grade": "C"
    },
    "ATL": {
      "battingRate": 0.382,
      "battingWon": 26,
      "battingAttempted": 68,
      "netOverturns": -9.3,
      "totalVsExpected": 0.8,
      "grade": "C"
    },
    "CLE": {
      "battingRate": 0.394,
      "battingWon": 37,
      "battingAttempted": 94,
      "netOverturns": -11.8,
      "totalVsExpected": -15.3,
      "grade": "C"
    },
    "LAA": {
      "battingRate": 0.42,
      "battingWon": 37,
      "battingAttempted": 88,
      "netOverturns": -12.6,
      "totalVsExpected": -2.9,
      "grade": "C"
    },
    "PIT": {
      "battingRate": 0.382,
      "battingWon": 34,
      "battingAttempted": 89,
      "netOverturns": -21.7,
      "totalVsExpected": -22.9,
      "grade": "C"
    },
    "COL": {
      "battingRate": 0.382,
      "battingWon": 34,
      "battingAttempted": 89,
      "netOverturns": -22.3,
      "totalVsExpected": -16.8,
      "grade": "C"
    }
  }
}