{
  "_note": "Canonical sport metadata for FIELD. Used by daily-brief.js and index.html (SPORT_META const). Update here to change emoji/labels everywhere. Do not hardcode sport emoji in individual scripts.",
  "NBA": {
    "emoji": "🏀",
    "entity": "&#127936;",
    "label": "NBA",
    "singular": "game",
    "plural": "games"
  },
  "NHL": {
    "emoji": "🏒",
    "entity": "&#127954;",
    "label": "NHL",
    "singular": "game",
    "plural": "games"
  },
  "MLB": {
    "emoji": "⚾",
    "entity": "&#9918;",
    "label": "MLB",
    "singular": "game",
    "plural": "games"
  },
  "WNBA": {
    "emoji": "🏀",
    "entity": "&#127936;",
    "label": "WNBA",
    "singular": "game",
    "plural": "games"
  },
  "AFL": {
    "emoji": "🏉",
    "entity": "&#127945;",
    "label": "AFL",
    "singular": "game",
    "plural": "games"
  },
  "Soccer": {
    "emoji": "⚽",
    "entity": "&#9917;",
    "label": "Soccer",
    "singular": "match",
    "plural": "matches"
  },
  "Tennis": {
    "emoji": "🎾",
    "entity": "&#127934;",
    "label": "Tennis",
    "singular": "match",
    "plural": "matches"
  },
  "NFL": {
    "emoji": "🏈",
    "entity": "&#127944;",
    "label": "NFL",
    "singular": "game",
    "plural": "games"
  }
}