{
  "probeTime": "20260527T164847Z",
  "results": {
    "cdn_game": {
      "status": 404,
      "preview": "<!DOCTYPE HTML PUBLIC \"-//IETF//DTD HTML 2.0//EN\">\n<html><head>\n<title>404 Not Found</title>\n</head><body>\n<h1>Not Found</h1>\n<p>The requested URL /ufl/game/ was not found on this server.</p>\n</body></html>\n"
    },
    "core_plays": {
      "status": 200,
      "preview": "{\"$ref\": \"http://sports.core.api.espn.com/v2/sports/football/leagues/ufl/events/401857557/competitions/401857557/plays?source=1&lang=en&region=us\", \"count\": 0, \"pageIndex\": 0, \"pageSize\": 25, \"pageCount\": 0, \"items\": []}",
      "count": 0
    },
    "core_drives": {
      "status": 200,
      "preview": "{\"count\": 0, \"pageIndex\": 0, \"pageSize\": 25, \"pageCount\": 0, \"items\": []}"
    },
    "summary_lang": {
      "status": 200,
      "has_drives": false,
      "keys": [
        "boxscore",
        "format",
        "gameInfo",
        "leaders",
        "broadcasts",
        "pickcenter",
        "odds",
        "againstTheSpread",
        "header",
        "winprobability",
        "videos",
        "wallclockAvailable",
        "meta",
        "news",
        "standings"
      ]
    },
    "upcoming_games": [
      {
        "id": "401857560",
        "name": "Dallas Renegades at St. Louis Battlehawks",
        "date": "2026-05-30T00:00Z"
      },
      {
        "id": "401857561",
        "name": "Houston Gamblers at Birmingham Stallions",
        "date": "2026-05-30T19:00Z"
      },
      {
        "id": "401857562",
        "name": "Orlando Storm at DC Defenders",
        "date": "2026-05-31T16:00Z"
      },
      {
        "id": "401857563",
        "name": "Louisville Kings at Columbus Aviators",
        "date": "2026-05-31T22:00Z"
      }
    ]
  }
}